[
  {
    "id": 101,
    "subject_id": 1,
    "subject_name": "Calculus",
    "doctor_id": 1,
    "doctor_name": "Dr. Ghada EL Taweel",
    "level": 1,
    "department": "General",
    "day": "Sunday",
    "timeslot_id": 1,
    "time_display": "9:00 AM",
    "location_id": 1,
    "location_name": "Lab 1A",
    "active": true,
    "confirmationComment": "ؤؤ"
  },
  {
    "id": 102,
    "subject_id": 2,
    "subject_name": "Computer Science",
    "doctor_id": 2,
    "doctor_name": "Dr. Mohamed Miad ",
    "level": 1,
    "department": "Cyber Security",
    "day": "Sunday",
    "timeslot_id": 5,
    "time_display": "10:00 AM",
    "location_id": 2,
    "location_name": "Lab 1B",
    "active": true,
    "confirmationComment": "ءء"
  },
  {
    "id": 103,
    "subject_id": 3,
    "subject_name": "Database Systems",
    "doctor_id": 3,
    "doctor_name": "Dr. Marwa Mohamed",
    "level": 1,
    "department": "General",
    "day": "Sunday",
    "timeslot_id": 5,
    "time_display": "10:00 AM",
    "location_id": 3,
    "location_name": "Lab 2A",
    "active": true
  },
  {
    "id": 104,
    "subject_id": 4,
    "subject_name": "Discrete Mathematics",
    "doctor_id": 4,
    "doctor_name": "Dr. Jihad Mohamed",
    "level": 1,
    "department": "Cyber Security",
    "day": "Sunday",
    "timeslot_id": 7,
    "time_display": "10:30 AM",
    "location_id": 4,
    "location_name": "Lab 2B",
    "active": true
  },
  {
    "id": 105,
    "subject_id": 5,
    "subject_name": "Information Systems",
    "doctor_id": 5,
    "doctor_name": "Dr. Hassan El Mahdy",
    "level": 1,
    "department": "Software Engineering",
    "day": "Monday",
    "timeslot_id": 1,
    "time_display": "9:00 AM",
    "location_id": 5,
    "location_name": "Lab 3A",
    "active": true
  },
  {
    "id": 106,
    "subject_id": 6,
    "subject_name": "Digital Logic Design",
    "doctor_id": 1,
    "doctor_name": "Dr. Ghada EL Taweel",
    "level": 1,
    "department": "Software Engineering",
    "day": "Monday",
    "timeslot_id": 3,
    "time_display": "9:30 AM",
    "location_id": 6,
    "location_name": "Lab 3B",
    "active": true
  },
  {
    "id": 107,
    "subject_id": 7,
    "subject_name": "Fundamentals of Programming",
    "doctor_id": 3,
    "doctor_name": "Dr. Marwa Mohamed",
    "level": 1,
    "department": "Artificial Intelligence",
    "day": "Monday",
    "timeslot_id": 5,
    "time_display": "10:00 AM",
    "location_id": 7,
    "location_name": "Room 1A",
    "active": true
  },
  {
    "id": 108,
    "subject_id": 8,
    "subject_name": "Linear Algebra",
    "doctor_id": 2,
    "doctor_name": "Dr. Mohamed Miad",
    "level": 1,
    "department": "Artificial Intelligence",
    "day": "Monday",
    "timeslot_id": 7,
    "time_display": "10:30 AM",
    "location_id": 8,
    "location_name": "Room 1B",
    "active": true
  },
  {
    "id": 109,
    "subject_id": 9,
    "subject_name": "Statistics",
    "doctor_id": 4,
    "doctor_name": "Dr. Jihad Mohamed",
    "level": 1,
    "department": "Bioinformatics",
    "day": "Tuesday",
    "timeslot_id": 1,
    "time_display": "9:00 AM",
    "location_id": 9,
    "location_name": "Room 2A",
    "active": true
  },
  {
    "id": 110,
    "subject_id": 10,
    "subject_name": "Systems Analysis and Design",
    "doctor_id": 5,
    "doctor_name": "Dr. Hassan El Mahdy",
    "level": 1,
    "department": "Bioinformatics",
    "day": "Tuesday",
    "timeslot_id": 3,
    "time_display": "9:30 AM",
    "location_id": 10,
    "location_name": "Room 2B",
    "active": true
  },
  {
    "id": 201,
    "subject_id": 11,
    "subject_name": "Data Structures",
    "doctor_id": 1,
    "doctor_name": "Dr. Ghada EL Taweel",
    "level": 2,
    "department": "General",
    "day": "Tuesday",
    "timeslot_id": 5,
    "time_display": "10:00 AM",
    "location_id": 11,
    "location_name": "Room 3A",
    "active": true
  },
  {
    "id": 202,
    "subject_id": 12,
    "subject_name": "Introduction to Information Technology",
    "doctor_id": 2,
    "doctor_name": "Dr. Mohamed Miad",
    "level": 2,
    "department": "Cyber Security",
    "day": "Tuesday",
    "timeslot_id": 7,
    "time_display": "10:30 AM",
    "location_id": 12,
    "location_name": "Room 3B",
    "active": true
  },
  {
    "id": 203,
    "subject_id": 13,
    "subject_name": "Object-Oriented Programming",
    "doctor_id": 3,
    "doctor_name": "Dr. Marwa Mohamed",
    "level": 2,
    "department": "General",
    "day": "Wednesday",
    "timeslot_id": 1,
    "time_display": "9:00 AM",
    "location_id": 1,
    "location_name": "Lab 1A",
    "active": true
  },
  {
    "id": 204,
    "subject_id": 14,
    "subject_name": "Stochastic Processes",
    "doctor_id": 4,
    "doctor_name": "Dr. Jihad Mohamed",
    "level": 2,
    "department": "Cyber Security",
    "day": "Wednesday",
    "timeslot_id": 3,
    "time_display": "9:30 AM",
    "location_id": 2,
    "location_name": "Lab 1B",
    "active": true
  },
  {
    "id": 205,
    "subject_id": 15,
    "subject_name": "Web Programming",
    "doctor_id": 5,
    "doctor_name": "Dr. Hassan El Mahdy",
    "level": 2,
    "department": "Software Engineering",
    "day": "Wednesday",
    "timeslot_id": 5,
    "time_display": "10:00 AM",
    "location_id": 3,
    "location_name": "Lab 2A",
    "active": true
  },
  {
    "id": 206,
    "subject_id": 16,
    "subject_name": "Advanced Mathematics",
    "doctor_id": 1,
    "doctor_name": "Dr. Ghada EL Taweel",
    "level": 2,
    "department": "Software Engineering",
    "day": "Wednesday",
    "timeslot_id": 7,
    "time_display": "10:30 AM",
    "location_id": 4,
    "location_name": "Lab 2B",
    "active": true
  },
  {
    "id": 207,
    "subject_id": 17,
    "subject_name": "Analysis of Algorithms",
    "doctor_id": 2,
    "doctor_name": "Dr. Mohamed Miad",
    "level": 4,
    "department": "Computer Science",
    "day": "Thursday",
    "timeslot_id": 1,
    "time_display": "9:00 AM",
    "location_id": 5,
    "location_name": "Lab 3A",
    "active": true
  },
  {
    "id": 208,
    "subject_id": 18,
    "subject_name": "Concepts of Programming Languages",
    "doctor_id": 2,
    "doctor_name": "Dr. Mohamed Miad",
    "level": 2,
    "department": "Artificial Intelligence",
    "day": "Thursday",
    "timeslot_id": 3,
    "time_display": "9:30 AM",
    "location_id": 6,
    "location_name": "Lab 3B",
    "active": true
  },
  {
    "id": 209,
    "subject_id": 19,
    "subject_name": "Electronic Business",
    "doctor_id": 4,
    "doctor_name": "Dr. Jihad Mohamed",
    "level": 2,
    "department": "Artificial Intelligence",
    "day": "Thursday",
    "timeslot_id": 5,
    "time_display": "10:00 AM",
    "location_id": 7,
    "location_name": "Room 1A",
    "active": true
  },
  {
    "id": 210,
    "subject_id": 20,
    "subject_name": "Ordinary Differential Equations",
    "doctor_id": 5,
    "doctor_name": "Dr. Hassan El Mahdy",
    "level": 2,
    "department": "Bioinformatics",
    "day": "Thursday",
    "timeslot_id": 7,
    "time_display": "10:30 AM",
    "location_id": 8,
    "location_name": "Room 1B",
    "active": true
  },
  {
    "id": 211,
    "subject_id": 21,
    "subject_name": "Physics",
    "doctor_id": 3,
    "doctor_name": "Dr. Marwa Mohamed",
    "level": 2,
    "department": "Bioinformatics",
    "day": "Thursday",
    "timeslot_id": 9,
    "time_display": "11:00 AM",
    "location_id": 9,
    "location_name": "Room 2A",
    "active": true
  },
  {
    "id": 301,
    "subject_id": 22,
    "subject_name": "Advanced Programming",
    "doctor_id": 2,
    "doctor_name": "Dr. Mohamed Miad",
    "level": 3,
    "department": "Computer Science",
    "day": "Saturday",
    "timeslot_id": 1,
    "time_display": "9:00 AM",
    "location_id": 10,
    "location_name": "Room 2B",
    "active": true
  },
  {
    "id": 302,
    "subject_id": 23,
    "subject_name": "Artificial Intelligence",
    "doctor_id": 3,
    "doctor_name": "Dr. Marwa Mohamed",
    "level": 3,
    "department": "Information Systems",
    "day": "Saturday",
    "timeslot_id": 3,
    "time_display": "9:30 AM",
    "location_id": 11,
    "location_name": "Room 3A",
    "active": true
  },
  {
    "id": 303,
    "subject_id": 24,
    "subject_name": "Assembly Language",
    "doctor_id": 4,
    "doctor_name": "Dr. Jihad Mohamed",
    "level": 3,
    "department": "Computer Science",
    "day": "Saturday",
    "timeslot_id": 5,
    "time_display": "10:00 AM",
    "location_id": 12,
    "location_name": "Room 3B",
    "active": true
  },
  {
    "id": 304,
    "subject_id": 25,
    "subject_name": "Computer Architecture",
    "doctor_id": 5,
    "doctor_name": "Dr. Hassan El Mahdy",
    "level": 3,
    "department": "Information Systems",
    "day": "Sunday",
    "timeslot_id": 9,
    "time_display": "11:00 AM",
    "location_id": 1,
    "location_name": "Lab 1A",
    "active": true
  },
  {
    "id": 305,
    "subject_id": 26,
    "subject_name": "Image Processing",
    "doctor_id": 1,
    "doctor_name": "Dr. Ghada EL Taweel",
    "level": 3,
    "department": "Artificial Intelligence",
    "day": "Sunday",
    "timeslot_id": 11,
    "time_display": "11:30 AM",
    "location_id": 2,
    "location_name": "Lab 1B",
    "active": true
  },
  {
    "id": 306,
    "subject_id": 27,
    "subject_name": "Operating Systems",
    "doctor_id": 4,
    "doctor_name": "Dr. Jihad Mohamed",
    "level": 3,
    "department": "Cyber Security",
    "day": "Sunday",
    "timeslot_id": 13,
    "time_display": "12:00 PM",
    "location_id": 3,
    "location_name": "Lab 2A",
    "active": true
  },
  {
    "id": 307,
    "subject_id": 28,
    "subject_name": "Compiler Design",
    "doctor_id": 3,
    "doctor_name": "Dr. Marwa Mohamed",
    "level": 3,
    "department": "Artificial Intelligence",
    "day": "Monday",
    "timeslot_id": 9,
    "time_display": "11:00 AM",
    "location_id": 4,
    "location_name": "Lab 2B",
    "active": true
  },
  {
    "id": 308,
    "subject_id": 29,
    "subject_name": "Graphic Logic Design",
    "doctor_id": 2,
    "doctor_name": "Dr. Mohamed Miad",
    "level": 3,
    "department": "Cyber Security",
    "day": "Monday",
    "timeslot_id": 11,
    "time_display": "11:30 AM",
    "location_id": 5,
    "location_name": "Lab 3A",
    "active": true
  },
  {
    "id": 309,
    "subject_id": 30,
    "subject_name": "Computer Networks",
    "doctor_id": 5,
    "doctor_name": "Dr. Hassan El Mahdy",
    "level": 3,
    "department": "Software Engineering",
    "day": "Monday",
    "timeslot_id": 13,
    "time_display": "12:00 PM",
    "location_id": 6,
    "location_name": "Lab 3B",
    "active": true
  },
  {
    "id": 310,
    "subject_id": 31,
    "subject_name": "Signal Processing",
    "doctor_id": 1,
    "doctor_name": "Dr. Ghada EL Taweel",
    "level": 3,
    "department": "Software Engineering",
    "day": "Monday",
    "timeslot_id": 15,
    "time_display": "12:30 PM",
    "location_id": 7,
    "location_name": "Room 1A",
    "active": true
  },
  {
    "id": 401,
    "subject_id": 32,
    "subject_name": "Simulation and Modeling",
    "doctor_id": 5,
    "doctor_name": "Dr. Hassan El Mahdy",
    "level": 4,
    "department": "Information Systems",
    "day": "Tuesday",
    "timeslot_id": 9,
    "time_display": "11:00 AM",
    "location_id": 8,
    "location_name": "Room 1B",
    "active": true
  },
  {
    "id": 402,
    "subject_id": 33,
    "subject_name": "Software Engineering",
    "doctor_id": 3,
    "doctor_name": "Dr. Marwa Mohamed",
    "level": 4,
    "department": "Cyber Security",
    "day": "Tuesday",
    "timeslot_id": 11,
    "time_display": "11:30 AM",
    "location_id": 9,
    "location_name": "Room 2A",
    "active": true
  },
  {
    "id": 403,
    "subject_id": 34,
    "subject_name": "Computer Vision",
    "doctor_id": 4,
    "doctor_name": "Dr. Jihad Mohamed",
    "level": 4,
    "department": "Software Engineering",
    "day": "Tuesday",
    "timeslot_id": 13,
    "time_display": "12:00 PM",
    "location_id": 10,
    "location_name": "Room 2B",
    "active": true
  },
  {
    "id": 404,
    "subject_id": 35,
    "subject_name": "Distributed Systems",
    "doctor_id": 5,
    "doctor_name": "Dr. Hassan El Mahdy",
    "level": 4,
    "department": "Computer Science",
    "day": "Wednesday",
    "timeslot_id": 9,
    "time_display": "11:00 AM",
    "location_id": 11,
    "location_name": "Room 3A",
    "active": true
  },
  {
    "id": 405,
    "subject_id": 36,
    "subject_name": "Dynamic Programming",
    "doctor_id": 1,
    "doctor_name": "Dr. Ghada EL Taweel",
    "level": 4,
    "department": "Software Engineering",
    "day": "Wednesday",
    "timeslot_id": 11,
    "time_display": "11:30 AM",
    "location_id": 12,
    "location_name": "Room 3B",
    "active": true
  },
  {
    "id": 406,
    "subject_id": 37,
    "subject_name": "Machine Learning",
    "doctor_id": 1,
    "doctor_name": "Dr. Ghada EL Taweel",
    "level": 4,
    "department": "Artificial Intelligence",
    "day": "Wednesday",
    "timeslot_id": 13,
    "time_display": "12:00 PM",
    "location_id": 1,
    "location_name": "Lab 1A",
    "active": true
  },
  {
    "id": 407,
    "subject_id": 38,
    "subject_name": "Mobile Communication",
    "doctor_id": 3,
    "doctor_name": "Dr. Marwa Mohamed",
    "level": 4,
    "department": "Cyber Security",
    "day": "Thursday",
    "timeslot_id": 11,
    "time_display": "11:30 AM",
    "location_id": 2,
    "location_name": "Lab 1B",
    "active": true
  },
  {
    "id": 408,
    "subject_id": 39,
    "subject_name": "Computer and Network Security",
    "doctor_id": 4,
    "doctor_name": "Dr. Jihad Mohamed",
    "level": 4,
    "department": "Software Engineering",
    "day": "Thursday",
    "timeslot_id": 13,
    "time_display": "12:00 PM",
    "location_id": 3,
    "location_name": "Lab 2A",
    "active": true
  },
  {
    "id": 409,
    "subject_id": 40,
    "subject_name": "Neural Networks and Deep Learning",
    "doctor_id": 2,
    "doctor_name": "Dr. Mohamed Miad",
    "level": 4,
    "department": "Artificial Intelligence",
    "day": "Thursday",
    "timeslot_id": 15,
    "time_display": "12:30 PM",
    "location_id": 4,
    "location_name": "Lab 2B",
    "active": true
  }
]